{"date": "03-12", "total_gigs": 81, "gigs": [{"date": "2014-03-12", "band": "Sweep The Leg", "venue": "The Wild Rover Tavern", "city": "Boston", "gigname": null, "score": 0.33944}, {"date": "2016-03-12", "band": "FUSE BOX", "venue": "Finna's Tavern", "city": "Kingston", "gigname": null, "score": 0.3486}, {"date": "2016-03-12", "band": "IDLE RUMORS", "venue": "Daddy's Beach Club", "city": "Hull", "gigname": null, "score": 0.35217}, {"date": "2016-03-12", "band": "Fun Box", "venue": "Dolly Shakers", "city": "Nashua", "gigname": null, "score": 0.29538}, {"date": "2017-03-12", "band": "EVERPRESENT", "venue": "Middle East - Upstairs", "city": "Cambridge", "gigname": "Everpresent, Big Time Kill, Rogozo, DJ Anomaly", "score": 0.38021}, {"date": "2017-03-12", "band": "Dioniso", "venue": "Middle East - Downstairs", "city": "Cambridge", "gigname": "Rawayana en conceirto", "score": 0.07818}, {"date": "2017-03-12", "band": "Rawayana", "venue": "Middle East - Downstairs", "city": "Cambridge", "gigname": "Rawayana en conceirto", "score": 0.07818}, {"date": "2017-03-12", "band": "Clandestino", "venue": "Middle East - Downstairs", "city": "Cambridge", "gigname": "Rawayana en conceirto", "score": 0.07818}, {"date": "2017-03-12", "band": "DJ Anomaly", "venue": "Middle East - Upstairs", "city": "Cambridge", "gigname": "Everpresent, Big Time Kill, Rogozo, DJ Anomaly", "score": 0.07636}, {"date": "2017-03-12", "band": "Rogozo", "venue": "Middle East - Upstairs", "city": "Cambridge", "gigname": "Everpresent, Big Time Kill, Rogozo, DJ Anomaly", "score": 0.07636}, {"date": "2017-03-12", "band": "Bigtime", "venue": "Middle East - Upstairs", "city": "Cambridge", "gigname": "Everpresent, Big Time Kill, Rogozo, DJ Anomaly", "score": 0.29174}, {"date": "2017-03-12", "band": "Shark Rock", "venue": "Middle East - Downstairs", "city": "Cambridge", "gigname": "Shark Rock", "score": 0.07818}, {"date": "2017-03-12", "band": "Sueños Rotos", "venue": "Middle East - Downstairs", "city": "Cambridge", "gigname": "Rawayana en conceirto", "score": 0.07818}, {"date": "2017-03-12", "band": "Fil Pacino", "venue": "Rivershed", "city": "Scituate", "gigname": "", "score": 0.38727}, {"date": "2017-03-12", "band": "Dioniso", "venue": "Middle East - Downstairs", "city": "Cambridge", "gigname": "Rawayana en concierto", "score": 0.40664}, {"date": "2017-03-12", "band": "Top Gun Academy: Declassified w/ Michael Savnat", "venue": "Middle East - Upstairs", "city": "Cambridge", "gigname": "Top Gun Academy: Declassified w/ Michael Savnat", "score": 0.07636}, {"date": "2017-03-12", "band": "Shark Rock", "venue": "Middle East - Upstairs", "city": "Cambridge", "gigname": "Shark Rock, Natalie Copeland, Brennan", "score": 0.07636}, {"date": "2017-03-12", "band": "Natalie Copeland", "venue": "Middle East - Upstairs", "city": "Cambridge", "gigname": "Shark Rock, Natalie Copeland, Brennan", "score": 0.07636}, {"date": "2017-03-12", "band": "Brennan", "venue": "Middle East - Upstairs", "city": "Cambridge", "gigname": "Shark Rock, Natalie Copeland, Brennan", "score": 0.07636}, {"date": "2017-03-12", "band": "Sunday Night Belly Dance - 18+ $5 Suggested Donation 8pm", "venue": "Middle East - Corner/Bakery", "city": "Cambridge", "gigname": "Sunday Night Belly Dance- 18+ $5 Suggested Donation 8 PM Doors", "score": 0.14818}, {"date": "2017-03-12", "band": "Jenn Grant", "venue": "Club Passim", "city": "Cambridge", "gigname": "Jenn Grant", "score": 0.14818}, {"date": "2017-03-12", "band": "CO/NTRY", "venue": "Great Scott", "city": "Boston", "gigname": "CO/NTRY", "score": 0.14727}, {"date": "2017-03-12", "band": "EVERPRESENT", "venue": "Middle East - Downstairs", "city": "Cambridge", "gigname": "Everpresent", "score": 0.38203}, {"date": "2017-03-12", "band": "Aine Minogue", "venue": "Thomas Crane Public Library", "city": "Quincy", "gigname": "Aine Minogue", "score": 0.00091}, {"date": "2017-03-12", "band": "Boston Youth Symphony Orchestra", "venue": "Boston Hatch Shell", "city": "Boston", "gigname": "Boston Youth Symphony Orchestra", "score": 0.07545}, {"date": "2017-03-12", "band": "Can't Swim", "venue": "Brighton Music Hall", "city": "Boston", "gigname": "Can't Swim", "score": 0.14818}, {"date": "2017-03-12", "band": "Light Years", "venue": "Brighton Music Hall", "city": "Boston", "gigname": "Can't Swim", "score": 0.14818}, {"date": "2017-03-12", "band": "Sleep On It", "venue": "Brighton Music Hall", "city": "Boston", "gigname": "Can't Swim", "score": 0.14818}, {"date": "2017-03-12", "band": "Devendra Banhart", "venue": "Royale", "city": "Boston", "gigname": "Devendra Banhart", "score": 0.14545}, {"date": "2017-03-12", "band": "Natalie MacMaster", "venue": "The Berklee Performance Center", "city": "Boston", "gigname": "Natalie MacMaster", "score": 0.12091}, {"date": "2017-03-12", "band": "Donnell Leahy", "venue": "The Berklee Performance Center", "city": "Boston", "gigname": "Natalie MacMaster", "score": 0.12091}, {"date": "2017-03-12", "band": "Greg Klyma", "venue": "Thunder Road", "city": "Somerville", "gigname": "Americana Sundays w/ Greg Klyma", "score": 0.24735}, {"date": "2017-03-12", "band": "RadioVolta", "venue": "Middle East - Downstairs", "city": "Cambridge", "gigname": "Rawayana en conceirto", "score": 0.07818}, {"date": "2017-03-12", "band": "The Heavy Pets", "venue": "O'Brien's Pub", "city": "Boston", "gigname": "the Heavies", "score": 0.07818}, {"date": "2017-03-12", "band": "The Dead Elect", "venue": "O'Brien's Pub", "city": "Boston", "gigname": "the Heavies", "score": 0.07818}, {"date": "2017-03-12", "band": "Wind in Sails", "venue": "O'Brien's Pub", "city": "Boston", "gigname": "the Heavies", "score": 0.07818}, {"date": "2017-03-12", "band": "Today Junior", "venue": "O'Brien's Pub", "city": "Boston", "gigname": "the Heavies", "score": 0.07818}, {"date": "2017-03-12", "band": "Bob Bandera", "venue": "The Jetty", "city": "Marshfield", "gigname": "Acoustic Brunch", "score": 0.50405}, {"date": "2017-03-12", "band": "The Jake Ash Band", "venue": "T-Bones", "city": "Plymouth", "gigname": "", "score": 0.34237}, {"date": "2017-03-12", "band": "missile girl", "venue": "Middle East - Upstairs", "city": "Cambridge", "gigname": "missile girl", "score": 0.07636}, {"date": "2018-03-12", "band": "Mo-Rice", "venue": "Middle East - Corner/Bakery", "city": "Cambridge", "gigname": "Mo-Rice", "score": 0.14818}, {"date": "2018-03-12", "band": "Mat Kerekes", "venue": "House of Blues Boston", "city": "Boston", "gigname": "Mat Kearney", "score": 0.14909}, {"date": "2018-03-12", "band": "Nightmare Of You", "venue": "Brighton Music Hall", "city": "Boston", "gigname": "Nightmares On Wax", "score": 0.14818}, {"date": "2018-03-12", "band": "SPECTRIS", "venue": "Once Lounge & Musichall", "city": "Somerville", "gigname": "Spectramotiv", "score": 0.44322}, {"date": "2018-03-12", "band": "Sophia Belle", "venue": "Once Lounge & Musichall", "city": "Somerville", "gigname": "Spectramotiv", "score": 0.14091}, {"date": "2018-03-12", "band": "Self Titled", "venue": "O'Brien's Pub", "city": "Boston", "gigname": "Self Titled", "score": 0.07818}, {"date": "2018-03-12", "band": "Ghosts of Sailors at Sea", "venue": "Great Scott", "city": "Boston", "gigname": "Ghosts of Sailors at Sea", "score": 0.14727}, {"date": "2018-03-12", "band": "filous", "venue": "House of Blues Boston", "city": "Boston", "gigname": "Mat Kearney", "score": 0.14909}, {"date": "2018-03-12", "band": "Andrew Bayer", "venue": "House of Blues Boston", "city": "Boston", "gigname": "Mat Kearney", "score": 0.14909}, {"date": "2018-03-12", "band": "Kyle Cook", "venue": "Thunder Road", "city": "Somerville", "gigname": "Kyle Cook", "score": 0.15273}, {"date": "2018-03-12", "band": "Rivers and Rust", "venue": "Thunder Road", "city": "Somerville", "gigname": "Rivers and Rust", "score": 0.15273}, {"date": "2018-03-12", "band": "Peripheral Sounds", "venue": "Middle East - Corner/Bakery", "city": "Cambridge", "gigname": "Peripheral Sounds", "score": 0.14818}, {"date": "2018-03-12", "band": "The Furniture (Boston)", "venue": "Middle East - Upstairs", "city": "Cambridge", "gigname": "The Furniture, Fantastic Liars", "score": 0.07636}, {"date": "2019-03-12", "band": "VALLEY", "venue": "Once Lounge & Musichall", "city": "Somerville", "gigname": "Mallcops", "score": 0.34706}, {"date": "2019-03-12", "band": "Tory Silver", "venue": "Great Scott", "city": "Boston", "gigname": "Jakals", "score": 0.14727}, {"date": "2019-03-12", "band": "Paper Citizen", "venue": "Great Scott", "city": "Boston", "gigname": "Jakals", "score": 0.14727}, {"date": "2019-03-12", "band": "Allison & Moon", "venue": "Midway Café", "city": "Boston", "gigname": "Allison & Moon", "score": 0.14727}, {"date": "2019-03-12", "band": "Miele", "venue": "Midway Café", "city": "Boston", "gigname": "Allison & Moon", "score": 0.14727}, {"date": "2019-03-12", "band": "Lock", "venue": "Midway Café", "city": "Boston", "gigname": "Allison & Moon", "score": 0.14727}, {"date": "2019-03-12", "band": "The Tossers", "venue": "Middle East - Upstairs", "city": "Cambridge", "gigname": "The Tossers", "score": 0.07636}, {"date": "2019-03-12", "band": "Palisades", "venue": "House of Blues Boston", "city": "Boston", "gigname": "Nothing More", "score": 0.14909}, {"date": "2019-03-12", "band": "Of Mice & Men", "venue": "House of Blues Boston", "city": "Boston", "gigname": "Nothing More", "score": 0.14909}, {"date": "2019-03-12", "band": "Nothing More", "venue": "House of Blues Boston", "city": "Boston", "gigname": "Nothing More", "score": 0.14909}, {"date": "2019-03-12", "band": "Sweet Petunia", "venue": "Thunder Road", "city": "Somerville", "gigname": "Caroline Guske, Tenfold Path, Copilot, Sweet Petunia", "score": 0.15273}, {"date": "2019-03-12", "band": "Copilot", "venue": "Thunder Road", "city": "Somerville", "gigname": "Caroline Guske, Tenfold Path, Copilot, Sweet Petunia", "score": 0.15273}, {"date": "2019-03-12", "band": "Tenfold Path", "venue": "Thunder Road", "city": "Somerville", "gigname": "Caroline Guske, Tenfold Path, Copilot, Sweet Petunia", "score": 0.15273}, {"date": "2019-03-12", "band": "Molsky's Mountain Drifters", "venue": "The Berklee Performance Center", "city": "Boston", "gigname": "Bruce Molsky", "score": 0.12091}, {"date": "2019-03-12", "band": "Bruce Molsky", "venue": "The Berklee Performance Center", "city": "Boston", "gigname": "Bruce Molsky", "score": 0.12091}, {"date": "2019-03-12", "band": "Samantha Crain", "venue": "Boston Rocks", "city": "Boston", "gigname": "Samantha Crain", "score": 0.10909}, {"date": "2019-03-12", "band": "Ben Rector", "venue": "Middle East - Upstairs", "city": "Cambridge", "gigname": "Hallelujah Chorus, RODØ, Ben Reggio", "score": 0.07636}, {"date": "2019-03-12", "band": "Marie Osmond", "venue": "Chevalier Theatre", "city": "Medford", "gigname": "Marie Osmond", "score": 0.10182}, {"date": "2019-03-12", "band": "OneManJamz", "venue": "Boston Rocks", "city": "Boston", "gigname": "OneManJamz", "score": 0.10909}, {"date": "2019-03-12", "band": "Daughters", "venue": "The Sinclair", "city": "Cambridge", "gigname": "Daughters", "score": 0.28482}, {"date": "2019-03-12", "band": "Badflower", "venue": "House of Blues Boston", "city": "Boston", "gigname": "Nothing More", "score": 0.14909}, {"date": "2019-03-12", "band": "Sierra Hull", "venue": "The Berklee Performance Center", "city": "Boston", "gigname": "Sierra Hull", "score": 0.12091}, {"date": "2019-03-12", "band": "We Three", "venue": "The Wilbur", "city": "Boston", "gigname": "We Three", "score": 0.12182}, {"date": "2019-03-12", "band": "Blue Manic", "venue": "O'Brien's Pub", "city": "Boston", "gigname": "Blue Manic", "score": 0.07818}, {"date": "2019-03-12", "band": "Jakals", "venue": "Great Scott", "city": "Boston", "gigname": "Jakals", "score": 0.14727}, {"date": "2019-03-12", "band": "Comedy Open Mic", "venue": "Middle East - Corner/Bakery", "city": "Cambridge", "gigname": "Comedy Open Mic", "score": 0.14818}, {"date": "2019-03-12", "band": "Hallelujah The Hills", "venue": "Middle East - Upstairs", "city": "Cambridge", "gigname": "Hallelujah Chorus, RODØ, Ben Reggio", "score": 0.2579}, {"date": "2019-03-12", "band": "RODØ", "venue": "Middle East - Upstairs", "city": "Cambridge", "gigname": "Hallelujah Chorus, RODØ, Ben Reggio", "score": 0.07636}]}