{"date": "04-13", "total_gigs": 128, "gigs": [{"date": "2013-04-13", "band": "Full Throttle", "venue": "Venus III", "city": "Hanson", "gigname": null, "score": 0.35336}, {"date": "2013-04-13", "band": "Haywire Davinci", "venue": "Slapshotz Sports Pub", "city": "Avon", "gigname": null, "score": 0.5514}, {"date": "2013-04-13", "band": "Reverse Curve", "venue": "Player's Sports Bar and Grille", "city": "ROCKLAND", "gigname": null, "score": 0.53294}, {"date": "2013-04-13", "band": "SLIDER", "venue": "Daddy's Beach Club", "city": "Hull", "gigname": null, "score": 0.38986}, {"date": "2013-04-13", "band": "Michele Rockwell Band", "venue": "Pier 37", "city": "New Bedford", "gigname": null, "score": 0.31077}, {"date": "2013-04-13", "band": "The 617", "venue": "The Tinker's Son", "city": "Norwell", "gigname": null, "score": 0.36595}, {"date": "2013-04-13", "band": "The EVA BRAUN Band", "venue": "Stix and Stones", "city": "Abington", "gigname": null, "score": 0.35923}, {"date": "2013-04-13", "band": "Chad LaMarsh", "venue": "Whippersnapper", "city": "Londonderry", "gigname": null, "score": 0.34692}, {"date": "2013-04-13", "band": "THE DAN LAWSON BAND", "venue": "Celley's Pub & Grub", "city": "Lynn", "gigname": null, "score": 0.36958}, {"date": "2013-04-13", "band": "Sound Tower", "venue": "The Fan Club", "city": "East Wareham", "gigname": null, "score": 0.33769}, {"date": "2013-04-13", "band": "MIKE GARVEY BAND", "venue": "The Next Page Blues Cafe", "city": "Weymouth", "gigname": null, "score": 0.33294}, {"date": "2013-04-13", "band": "Mark & Wendy", "venue": "Meadow Brook Restaurant", "city": "Hanson", "gigname": null, "score": 0.31154}, {"date": "2013-04-13", "band": "Blind Ambition", "venue": "Barretts Ale House", "city": "Bridgewater", "gigname": null, "score": 0.36735}, {"date": "2014-04-13", "band": "The Joe Mack Band", "venue": "Celley's Pub & Grub", "city": "Lynn", "gigname": null, "score": 0.37419}, {"date": "2017-04-13", "band": "Tennyson", "venue": "The Sinclair", "city": "Cambridge", "gigname": "Big Wild", "score": 0.28482}, {"date": "2017-04-13", "band": "Anna Freitas", "venue": "Middle East - Upstairs", "city": "Cambridge", "gigname": "Anna Wise, Madison McFerrin, Leon Waldo", "score": 0.41713}, {"date": "2017-04-13", "band": "Madison McFerrin", "venue": "Middle East - Upstairs", "city": "Cambridge", "gigname": "Anna Wise, Madison McFerrin, Leon Waldo", "score": 0.07636}, {"date": "2017-04-13", "band": "Leon Waldo", "venue": "Middle East - Upstairs", "city": "Cambridge", "gigname": "Anna Wise, Madison McFerrin, Leon Waldo", "score": 0.07636}, {"date": "2017-04-13", "band": "Obituary", "venue": "Paradise Rock Club", "city": "Boston", "gigname": "Obituary", "score": 0.14364}, {"date": "2017-04-13", "band": "Kreator", "venue": "Paradise Rock Club", "city": "Boston", "gigname": "Obituary", "score": 0.14364}, {"date": "2017-04-13", "band": "The Rumjacks", "venue": "O'Brien's Pub", "city": "Boston", "gigname": "The Rumjacks", "score": 0.07818}, {"date": "2017-04-13", "band": "Dave Davies", "venue": "Natick Center For The Arts", "city": "Natick", "gigname": "Dave Davies", "score": 0.10545}, {"date": "2017-04-13", "band": "North By North", "venue": "The Plough & Stars", "city": "Cambridge", "gigname": "North By North", "score": 0.10909}, {"date": "2017-04-13", "band": "Evening Darling", "venue": "PA's Lounge", "city": "Somerville", "gigname": "Evening Darling", "score": 0.07182}, {"date": "2017-04-13", "band": "Pure Pupil", "venue": "PA's Lounge", "city": "Somerville", "gigname": "Evening Darling", "score": 0.07182}, {"date": "2017-04-13", "band": "The Silver Mirrors", "venue": "PA's Lounge", "city": "Somerville", "gigname": "Evening Darling", "score": 0.21797}, {"date": "2017-04-13", "band": "Imagined Herbal Flows", "venue": "The Sinclair", "city": "Cambridge", "gigname": "Big Wild", "score": 0.14636}, {"date": "2017-04-13", "band": "Modern English", "venue": "Brighton Music Hall", "city": "Boston", "gigname": "Modern English", "score": 0.14818}, {"date": "2017-04-13", "band": "Anna Freitas", "venue": "Middle East - Downstairs", "city": "Cambridge", "gigname": "Anna Wise", "score": 0.41895}, {"date": "2017-04-13", "band": "Spotted Tiger", "venue": "Lizard Lounge", "city": "Cambridge", "gigname": "Spotted Tiger", "score": 0.14727}, {"date": "2017-04-13", "band": "Lady Pills", "venue": "Great Scott", "city": "Boston", "gigname": "Lady Pills", "score": 0.14727}, {"date": "2017-04-13", "band": "Damn Tall Buildings", "venue": "Atwood's Tavern", "city": "Cambridge", "gigname": "Damn Tall Buildings", "score": 0.14909}, {"date": "2017-04-13", "band": "Saucy", "venue": "Middle East - Upstairs", "city": "Cambridge", "gigname": "SAUCY E04 - 10PM 21+ $5", "score": 0.07636}, {"date": "2017-04-13", "band": "Heroes", "venue": "Middle East - Downstairs", "city": "Cambridge", "gigname": "Herobust, Voltran, Under Lux", "score": 0.21818}, {"date": "2017-04-13", "band": "John Taglieri", "venue": "The Tinker's Son", "city": "Norwell", "gigname": "", "score": 0.34672}, {"date": "2017-04-13", "band": "The Joneses", "venue": "Tavern at the Post", "city": "Hanson", "gigname": null, "score": 0.34265}, {"date": "2017-04-13", "band": "Populace", "venue": "Middle East - Corner/Bakery", "city": "Cambridge", "gigname": "Populace", "score": 0.14818}, {"date": "2017-04-13", "band": "Mammal Dap", "venue": "Thunder Road", "city": "Somerville", "gigname": "Mammal Dap", "score": 0.15273}, {"date": "2017-04-13", "band": "Fil Pacino", "venue": "Fireside Grille", "city": "Middleborough", "gigname": "", "score": 0.35}, {"date": "2017-04-13", "band": "Under Lux", "venue": "Middle East - Downstairs", "city": "Cambridge", "gigname": "Herobust, Voltran, Under Lux", "score": 0.07818}, {"date": "2017-04-13", "band": "Voltran", "venue": "Middle East - Downstairs", "city": "Cambridge", "gigname": "Herobust, Voltran, Under Lux", "score": 0.07818}, {"date": "2018-04-13", "band": "Radio Honey", "venue": "Funky Murphy's Bar and Grill", "city": "Marlboro", "gigname": "RH at Funky Murphy's", "score": 0.44482}, {"date": "2018-04-13", "band": "Replacire", "venue": "Middle East - Upstairs", "city": "Cambridge", "gigname": "Replacire, Cognitive, Mourned, Unflesh", "score": 0.07636}, {"date": "2018-04-13", "band": "Cognitive", "venue": "Middle East - Upstairs", "city": "Cambridge", "gigname": "Replacire, Cognitive, Mourned, Unflesh", "score": 0.07636}, {"date": "2018-04-13", "band": "Unflesh", "venue": "Middle East - Upstairs", "city": "Cambridge", "gigname": "Replacire, Cognitive, Mourned, Unflesh", "score": 0.07636}, {"date": "2018-04-13", "band": "The Van Burens", "venue": "Middle East - Corner/Bakery", "city": "Cambridge", "gigname": "The Van Burens", "score": 0.14818}, {"date": "2018-04-13", "band": "The Nth Power", "venue": "Thunder Road", "city": "Somerville", "gigname": "The Nth Power", "score": 0.15273}, {"date": "2018-04-13", "band": "The Fat City Band", "venue": "The Jetty", "city": "Marshfield", "gigname": "Ranch House Revival", "score": 0.53636}, {"date": "2018-04-13", "band": "DJ Rugged One", "venue": "Middle East - Upstairs", "city": "Cambridge", "gigname": "90s Dance Night with DJ Rugged One", "score": 0.07636}, {"date": "2018-04-13", "band": "James Bay", "venue": "Paradise Rock Club", "city": "Boston", "gigname": "James TW", "score": 0.14364}, {"date": "2018-04-13", "band": "Houston Bernard Band", "venue": "Loretta's Last Call", "city": "Boston", "gigname": "Houston Bernard Band", "score": 0.14727}, {"date": "2018-04-13", "band": "Bucky Harris", "venue": "The Victory Grille", "city": "Dedham", "gigname": "Bucky O'Hare", "score": 0.0}, {"date": "2018-04-13", "band": "Grace Weber", "venue": "Royale", "city": "Boston", "gigname": "Thirdstory", "score": 0.14545}, {"date": "2018-04-13", "band": "Andy Grammer", "venue": "Paradise Rock Club", "city": "Boston", "gigname": "Andy Grammer", "score": 0.14364}, {"date": "2018-04-13", "band": "Dayme Arocena", "venue": "The Berklee Performance Center", "city": "Boston", "gigname": "Dayme Arocena", "score": 0.12091}, {"date": "2018-04-13", "band": "Troy Bennett", "venue": "Boston State House", "city": "Boston", "gigname": "Tony Bennett", "score": 0.30231}, {"date": "2018-04-13", "band": "Karen Zanes", "venue": "Dedham Square Coffeehouse", "city": "Dedham", "gigname": "Karen Zanes", "score": 0.08182}, {"date": "2018-04-13", "band": "Rob Byrd", "venue": "Dedham Square Coffeehouse", "city": "Dedham", "gigname": "Karen Zanes", "score": 0.12028}, {"date": "2018-04-13", "band": "Frankie Valli & The Four Seasons", "venue": "Chevalier Theatre", "city": "Medford", "gigname": "Frankie Valli & The Four Seasons", "score": 0.10182}, {"date": "2018-04-13", "band": "Frankie Valli", "venue": "Chevalier Theatre", "city": "Medford", "gigname": "Frankie Valli & The Four Seasons", "score": 0.10182}, {"date": "2018-04-13", "band": "Audra McDonald", "venue": "Boston Hatch Shell", "city": "Boston", "gigname": "Audra McDonald", "score": 0.07545}, {"date": "2018-04-13", "band": "Della Mae", "venue": "The Sinclair", "city": "Cambridge", "gigname": "Della Mae", "score": 0.14636}, {"date": "2018-04-13", "band": "Cognitive", "venue": "Middle East - Downstairs", "city": "Cambridge", "gigname": "Cognitive", "score": 0.07818}, {"date": "2018-04-13", "band": "Replacire", "venue": "Middle East - Downstairs", "city": "Cambridge", "gigname": "Cognitive", "score": 0.07818}, {"date": "2018-04-13", "band": "Threat Level Burgundy", "venue": "O'Brien's Pub", "city": "Boston", "gigname": "Threat Level Burgundy", "score": 0.07818}, {"date": "2018-04-13", "band": "The New Limits", "venue": "O'Brien's Pub", "city": "Boston", "gigname": "Threat Level Burgundy", "score": 0.07818}, {"date": "2018-04-13", "band": "Abraskadabra", "venue": "O'Brien's Pub", "city": "Boston", "gigname": "Threat Level Burgundy", "score": 0.07818}, {"date": "2018-04-13", "band": "Espinoza Paz", "venue": "Wonderland Ballroom", "city": "Revere", "gigname": "Espinoza Paz", "score": 0.09273}, {"date": "2018-04-13", "band": "3LAU", "venue": "The Grand Canal", "city": "Boston", "gigname": "3LAU", "score": 0.03909}, {"date": "2018-04-13", "band": "Malaa", "venue": "Royale", "city": "Boston", "gigname": "Malaa", "score": 0.14545}, {"date": "2018-04-13", "band": "The Curtis Mayflower", "venue": "Atwood's Tavern", "city": "Cambridge", "gigname": "The Curtis Mayflower", "score": 0.14909}, {"date": "2018-04-13", "band": "Thick Shakes", "venue": "Harvard Square", "city": "Cambridge", "gigname": "THICK", "score": 0.22237}, {"date": "2018-04-13", "band": "Dog", "venue": "Harvard Square", "city": "Cambridge", "gigname": "THICK", "score": 0.04545}, {"date": "2018-04-13", "band": "evicshen", "venue": "Harvard Square", "city": "Cambridge", "gigname": "THICK", "score": 0.04545}, {"date": "2018-04-13", "band": "[wimp]", "venue": "Harvard Square", "city": "Cambridge", "gigname": "THICK", "score": 0.04545}, {"date": "2018-04-13", "band": "Squitch", "venue": "Harvard Square", "city": "Cambridge", "gigname": "THICK", "score": 0.04545}, {"date": "2018-04-13", "band": "Puppy Problems", "venue": "Harvard Square", "city": "Cambridge", "gigname": "THICK", "score": 0.04545}, {"date": "2018-04-13", "band": "Brennan", "venue": "Harvard Square", "city": "Cambridge", "gigname": "THICK", "score": 0.04545}, {"date": "2018-04-13", "band": "Aviator", "venue": "Sammy's Patio", "city": "Revere", "gigname": "Aviations", "score": 0.10182}, {"date": "2018-04-13", "band": "Circuitry", "venue": "Sammy's Patio", "city": "Revere", "gigname": "Aviations", "score": 0.10182}, {"date": "2018-04-13", "band": "The Sauce", "venue": "Sammy's Patio", "city": "Revere", "gigname": "Aviations", "score": 0.16413}, {"date": "2018-04-13", "band": "Mind Yeti", "venue": "Great Scott", "city": "Boston", "gigname": "Mind Yeti", "score": 0.14727}, {"date": "2018-04-13", "band": "Planet of Adventure", "venue": "Great Scott", "city": "Boston", "gigname": "Mind Yeti", "score": 0.14727}, {"date": "2018-04-13", "band": "Inverter", "venue": "Great Scott", "city": "Boston", "gigname": "Mind Yeti", "score": 0.14727}, {"date": "2018-04-13", "band": "Xmortis Über ", "venue": "Middle East - Downstairs", "city": "Cambridge", "gigname": "XMORTIS Apocalypse", "score": 0.07818}, {"date": "2019-04-13", "band": "Pedestrian Deposit", "venue": "The Elks Lodge", "city": "Marshfield", "gigname": "Pedestrian Deposit", "score": 0.0}, {"date": "2019-04-13", "band": "M Ax Noi Mach", "venue": "The Elks Lodge", "city": "Marshfield", "gigname": "Pedestrian Deposit", "score": 0.0}, {"date": "2019-04-13", "band": "Twin Shadow", "venue": "Middle East - Downstairs", "city": "Cambridge", "gigname": "The Pineapple Jam", "score": 0.07818}, {"date": "2019-04-13", "band": "Serena Z", "venue": "Berklee Cafe", "city": "boston", "gigname": "Serena Z", "score": 0.05455}, {"date": "2019-04-13", "band": "Twin Shadow", "venue": "Middle East - Upstairs", "city": "Cambridge", "gigname": "Twin Fish", "score": 0.07636}, {"date": "2019-04-13", "band": "DJ Seth Breezy", "venue": "Middle East - Downstairs", "city": "Cambridge", "gigname": "MOBD with DJ Seth Breezy", "score": 0.07818}, {"date": "2019-04-13", "band": "Moe Dee", "venue": "Middle East - Upstairs", "city": "Cambridge", "gigname": "The Get Down - Classic Dance Music ft. Moe Dee", "score": 0.07636}, {"date": "2019-04-13", "band": "Call of Booty", "venue": "Middle East - Corner/Bakery", "city": "Cambridge", "gigname": "Call of Booty", "score": 0.14818}, {"date": "2019-04-13", "band": "Jim Sylvia", "venue": "The Jetty", "city": "Marshfield", "gigname": "Happy Hour", "score": 0.34636}, {"date": "2019-04-13", "band": "Jim Plunkett", "venue": "The Jetty", "city": "Marshfield", "gigname": "Ranch House Revival", "score": 0.34636}, {"date": "2019-04-13", "band": "hareld group", "venue": "Regent Theatre", "city": "Arlington", "gigname": "The Real Group", "score": 0.38028}, {"date": "2019-04-13", "band": "The Synthwave", "venue": "Middle East - Downstairs", "city": "Cambridge", "gigname": "Retrowave", "score": 0.07818}, {"date": "2019-04-13", "band": "Retrowave", "venue": "Middle East - Downstairs", "city": "Cambridge", "gigname": "Retrowave", "score": 0.07818}, {"date": "2019-04-13", "band": "Sona", "venue": "Great Scott", "city": "Boston", "gigname": "Telekinesis", "score": 0.14727}, {"date": "2019-04-13", "band": "DeDe & the Jazz Cats", "venue": "Middle East - Corner/Bakery", "city": "Cambridge", "gigname": "Brunch Entertainment w/ DeDe & the Jazz Cats", "score": 0.14818}, {"date": "2019-04-13", "band": "Telekinesis", "venue": "Great Scott", "city": "Boston", "gigname": "Telekinesis", "score": 0.14727}, {"date": "2019-04-13", "band": "2Minute Minor", "venue": "O'Brien's Pub", "city": "Boston", "gigname": "2Minute Minor", "score": 0.07818}, {"date": "2019-04-13", "band": "Ben Williams", "venue": "Scullers Jazz Club", "city": "Boston", "gigname": "Buster Williams", "score": 0.12273}, {"date": "2019-04-13", "band": "Dakha Brakha", "venue": "Somerville Theatre", "city": "Somerville", "gigname": "Dakha Brakha", "score": 0.04636}, {"date": "2019-04-13", "band": "Frankie Valli", "venue": "Chevalier Theatre", "city": "Medford", "gigname": "Frankie Valli", "score": 0.10182}, {"date": "2019-04-13", "band": "Iris Lune", "venue": "Regent Theatre", "city": "Arlington", "gigname": "Iris", "score": 0.18182}, {"date": "2019-04-13", "band": "Nick Mason", "venue": "The Orpheum Theater", "city": "Boston", "gigname": "Nick Mason", "score": 0.10091}, {"date": "2019-04-13", "band": "The Motet", "venue": "Natick Center For The Arts", "city": "Natick", "gigname": "The Motels", "score": 0.10545}, {"date": "2019-04-13", "band": "Lil Tracy", "venue": "Brighton Music Hall", "city": "Boston", "gigname": "Lil Tracy", "score": 0.14818}, {"date": "2019-04-13", "band": "Roy Sludge", "venue": "Atwood's Tavern", "city": "Cambridge", "gigname": "Roy Sludge", "score": 0.14909}, {"date": "2019-04-13", "band": "Dream Surgery", "venue": "The Elks Lodge", "city": "Marshfield", "gigname": "Pedestrian Deposit", "score": 0.0}, {"date": "2019-04-13", "band": "Network Glass", "venue": "The Elks Lodge", "city": "Marshfield", "gigname": "Pedestrian Deposit", "score": 0.0}, {"date": "2019-04-13", "band": "Isolde Touch", "venue": "The Elks Lodge", "city": "Marshfield", "gigname": "Pedestrian Deposit", "score": 0.0}, {"date": "2019-04-13", "band": "Universal Cell Unlock", "venue": "The Elks Lodge", "city": "Marshfield", "gigname": "Pedestrian Deposit", "score": 0.0}, {"date": "2019-04-13", "band": "Arthur Nasson", "venue": "CambridgeSide Galleria", "city": "Cambridge", "gigname": "Arthur Nasson", "score": 0.08455}, {"date": "2019-04-13", "band": "Kris Rodgers", "venue": "Sally OBrien", "city": "Somerville", "gigname": "Stop Calling Me Frank", "score": 0.11091}, {"date": "2019-04-13", "band": "Boston Youth Symphony Orchestra", "venue": "Boston Hatch Shell", "city": "Boston", "gigname": "Boston Symphony Orchestra", "score": 0.07545}, {"date": "2019-04-13", "band": "Gustavo Dudamel", "venue": "Boston Hatch Shell", "city": "Boston", "gigname": "Boston Symphony Orchestra", "score": 0.07545}, {"date": "2019-04-13", "band": "Magen Tracy", "venue": "BIRN Alive!", "city": "Boston", "gigname": "Magen Tracy", "score": 0.08091}, {"date": "2019-04-13", "band": "The Ruta Beggars", "venue": "Club Passim", "city": "Cambridge", "gigname": "down home up here bluegrass festival 2019", "score": 0.14818}, {"date": "2019-04-13", "band": "Arts Fishing Club", "venue": "Boston College", "city": "Chestnut Hill", "gigname": "Arts Fishing Club", "score": -0.00636}, {"date": "2019-04-13", "band": "Bruno", "venue": "Middle East - Corner/Bakery", "city": "Cambridge", "gigname": "Brunch Entertainment w/ Jimmy Craven", "score": 0.14818}, {"date": "2019-04-13", "band": "Otis Grove", "venue": "Thunder Road", "city": "Somerville", "gigname": "Otis Grove", "score": 0.44658}, {"date": "2019-04-13", "band": "DJ John Volitans", "venue": "Middle East - Upstairs", "city": "Cambridge", "gigname": "OVERDRIVE: Retrowave / Electropop / Synthwave", "score": 0.07636}, {"date": "2019-04-13", "band": "DJ J-808", "venue": "Middle East - Upstairs", "city": "Cambridge", "gigname": "OVERDRIVE: Retrowave / Electropop / Synthwave", "score": 0.07636}, {"date": "2019-04-13", "band": "Brad Marino", "venue": "Sally OBrien", "city": "Somerville", "gigname": "Stop Calling Me Frank", "score": 0.11091}, {"date": "2019-04-13", "band": "Chachi", "venue": "The Grand Canal", "city": "Boston", "gigname": "Chachi", "score": 0.26909}, {"date": "2019-04-13", "band": "Stop Calling Me Frank", "venue": "Sally OBrien", "city": "Somerville", "gigname": "Stop Calling Me Frank", "score": 0.11091}]}