{"date": "10-10", "total_gigs": 67, "gigs": [{"date": "2012-10-10", "band": "MARI'S KARAOKE", "venue": "Mari's Place", "city": "Quincy", "gigname": null}, {"date": "2013-10-10", "band": "The Joe Mack Band", "venue": "Franco American Club n", "city": "Beverly", "gigname": null}, {"date": "2013-10-10", "band": "Whiskey Wild", "venue": "Toby Keiths", "city": "Foxborough", "gigname": null}, {"date": "2013-10-10", "band": "John Ridlon", "venue": "JP Ryan's ", "city": "Abington", "gigname": null}, {"date": "2014-10-10", "band": "The 617", "venue": "TK O'Malley's Sports Cafe", "city": "Scituate", "gigname": null}, {"date": "2014-10-10", "band": "Outburst", "venue": "Skybox", "city": "Tewksbury", "gigname": null}, {"date": "2015-10-10", "band": "Hypercane", "venue": "The Derryfield Country Club", "city": "Manchester", "gigname": null}, {"date": "2015-10-10", "band": "The 617", "venue": "Mr. Dooley's Tavern", "city": "Cohasset", "gigname": null}, {"date": "2015-10-10", "band": "Jenny & The Nightlife", "venue": "Venus III", "city": "Hanson", "gigname": null}, {"date": "2015-10-10", "band": "Alpha Road", "venue": "Harry's Pub & Grill", "city": "Brockton", "gigname": null}, {"date": "2017-10-10", "band": "Timeflies", "venue": "House of Blues Boston", "city": "Boston", "gigname": "Timeflies"}, {"date": "2017-10-10", "band": "Physical Culture", "venue": "Middle East - Upstairs", "city": "Cambridge", "gigname": "Physical Culture"}, {"date": "2017-10-10", "band": "The Dusty 45s", "venue": "The Burren", "city": "Somerville", "gigname": "The Dusty 45s"}, {"date": "2017-10-10", "band": "Against Me!", "venue": "Paradise Rock Club", "city": "Boston", "gigname": "Against Me!"}, {"date": "2017-10-10", "band": "Bleached", "venue": "Paradise Rock Club", "city": "Boston", "gigname": "Against Me!"}, {"date": "2017-10-10", "band": "The Dirty Nil", "venue": "Paradise Rock Club", "city": "Boston", "gigname": "Against Me!"}, {"date": "2017-10-10", "band": "Dabin", "venue": "House of Blues Boston", "city": "Boston", "gigname": "Timeflies"}, {"date": "2017-10-10", "band": "Loote", "venue": "House of Blues Boston", "city": "Boston", "gigname": "Timeflies"}, {"date": "2017-10-10", "band": "Garry Tallent", "venue": "Royale", "city": "Boston", "gigname": "Gary Allan"}, {"date": "2017-10-10", "band": "Big Jon & The Mattress Factory", "venue": "Middle East - Upstairs", "city": "Cambridge", "gigname": "The Stone Foxes"}, {"date": "2017-10-10", "band": "Nai Palm", "venue": "Brighton Music Hall", "city": "Boston", "gigname": "Nai Palm"}, {"date": "2017-10-10", "band": "Wild Ponies", "venue": "Club Passim", "city": "Cambridge", "gigname": "Wild Ponies"}, {"date": "2017-10-10", "band": "Ninth Degree", "venue": "The Berklee Performance Center", "city": "Boston", "gigname": "7th Degree"}, {"date": "2017-10-10", "band": "Sun Seeker", "venue": "Great Scott", "city": "Boston", "gigname": "Sun Seeker"}, {"date": "2017-10-10", "band": "Billy Woodward", "venue": "Lizard Lounge", "city": "Cambridge", "gigname": "Billy Woodward"}, {"date": "2017-10-10", "band": "Trombone Shorty & Orleans Avenue", "venue": "The Orpheum Theater", "city": "Boston", "gigname": "Trombone Shorty & Orleans Avenue"}, {"date": "2017-10-10", "band": "OZLO", "venue": "O'Brien's Pub", "city": "Boston", "gigname": "Zanois"}, {"date": "2017-10-10", "band": "Zanois", "venue": "O'Brien's Pub", "city": "Boston", "gigname": "Zanois"}, {"date": "2017-10-10", "band": "The Fritz (US)", "venue": "Wonder Bar", "city": "Allston", "gigname": "The Fritz (US)"}, {"date": "2017-10-10", "band": "TOKiMONSTA", "venue": "The Sinclair", "city": "Cambridge", "gigname": "TOKiMONSTA"}, {"date": "2017-10-10", "band": "Weekend Greg", "venue": "O'Brien's Pub", "city": "Boston", "gigname": "Zanois"}, {"date": "2017-10-10", "band": "The Michael Character", "venue": "O'Brien's Pub", "city": "Boston", "gigname": "Zanois"}, {"date": "2017-10-10", "band": "Squitch", "venue": "O'Brien's Pub", "city": "Boston", "gigname": "Zanois"}, {"date": "2017-10-10", "band": "Sidney Gish", "venue": "O'Brien's Pub", "city": "Boston", "gigname": "Zanois"}, {"date": "2017-10-10", "band": "Torus", "venue": "Thunder Road", "city": "Somerville", "gigname": "Torus"}, {"date": "2017-10-10", "band": "Anderson Comedy Presents #MIDEASTCORN", "venue": "Middle East - Corner/Bakery", "city": "Cambridge", "gigname": "Anderson Comedy Presents #MIDEASTCORN"}, {"date": "2017-10-10", "band": "Kooked Out", "venue": "Middle East - Upstairs", "city": "Cambridge", "gigname": "The Stone Foxes, Big Jon and the Mattress Factory, Kooked Out"}, {"date": "2017-10-10", "band": "Stone Leaf", "venue": "Middle East - Upstairs", "city": "Cambridge", "gigname": "The Stone Foxes, Big Jon and the Mattress Factory, Kooked Out"}, {"date": "2017-10-10", "band": "Drunk Education", "venue": "Middle East - Upstairs", "city": "Cambridge", "gigname": "Drunk Education ft. JPat Brown, Nina Corcoran, Claudia Morales, Mellisa Nierman"}, {"date": "2017-10-10", "band": "Food Coupon", "venue": "Middle East - Upstairs", "city": "Cambridge", "gigname": "Food Coupon"}, {"date": "2018-10-10", "band": "J-RO", "venue": "Middle East - Upstairs", "city": "Cambridge", "gigname": "Section D b2b J-Ro, DailyVegetable, with Special Guest: Lil Chemist"}, {"date": "2018-10-10", "band": "DailyVegetable", "venue": "Middle East - Upstairs", "city": "Cambridge", "gigname": "Section D b2b J-Ro, DailyVegetable, with Special Guest: Lil Chemist"}, {"date": "2018-10-10", "band": "Lil West", "venue": "Middle East - Upstairs", "city": "Cambridge", "gigname": "Section D b2b J-Ro, DailyVegetable, with Special Guest: Lil Chemist"}, {"date": "2018-10-10", "band": "Happy Little Clouds", "venue": "Atwood's Tavern", "city": "Cambridge", "gigname": "The Beths"}, {"date": "2018-10-10", "band": "Dee Zaster", "venue": "Lizard Lounge", "city": "Cambridge", "gigname": "Dennis Brennan Band"}, {"date": "2018-10-10", "band": "Denzel Curry", "venue": "Paradise Rock Club", "city": "Boston", "gigname": "Denzel Curry"}, {"date": "2018-10-10", "band": "Big Eyes", "venue": "Royale", "city": "Boston", "gigname": "Joyce Manor"}, {"date": "2018-10-10", "band": "Vundabar", "venue": "Royale", "city": "Boston", "gigname": "Joyce Manor"}, {"date": "2018-10-10", "band": "Living With Lions", "venue": "Middle East - Upstairs", "city": "Cambridge", "gigname": "Living With Lions"}, {"date": "2018-10-10", "band": "Paul McDonald", "venue": "The Sinclair", "city": "Cambridge", "gigname": "Emily Kinney"}, {"date": "2018-10-10", "band": "Such Gold", "venue": "Middle East - Downstairs", "city": "Cambridge", "gigname": "Living With Lions"}, {"date": "2018-10-10", "band": "Suffer on Acid", "venue": "O'Brien's Pub", "city": "Boston", "gigname": "Vaulted"}, {"date": "2018-10-10", "band": "Gog", "venue": "O'Brien's Pub", "city": "Boston", "gigname": "Vaulted"}, {"date": "2018-10-10", "band": "Living With Lions", "venue": "Middle East - Downstairs", "city": "Cambridge", "gigname": "Living With Lions"}, {"date": "2018-10-10", "band": "Sharaya Summers", "venue": "Brighton Music Hall", "city": "Boston", "gigname": "Milo Greene"}, {"date": "2018-10-10", "band": "Milo Greene", "venue": "Brighton Music Hall", "city": "Boston", "gigname": "Milo Greene"}, {"date": "2018-10-10", "band": "Mark Erelli", "venue": "Club Passim", "city": "Cambridge", "gigname": "Lauren Balthrop"}, {"date": "2018-10-10", "band": "Dinty Child", "venue": "Club Passim", "city": "Cambridge", "gigname": "Lauren Balthrop"}, {"date": "2018-10-10", "band": "Bearly Dead - A Tribute To The Grateful Dead", "venue": "Thunder Road", "city": "Somerville", "gigname": "Bearly Dead - A Tribute To The Grateful Dead"}, {"date": "2018-10-10", "band": "Mikaela Davis", "venue": "Great Scott", "city": "Boston", "gigname": "Mikaela Davis"}, {"date": "2018-10-10", "band": "Jill McCracken", "venue": "Great Scott", "city": "Boston", "gigname": "Mikaela Davis"}, {"date": "2018-10-10", "band": "Nathan Kalish", "venue": "State Park Bar", "city": "Cambridge", "gigname": "Nathan Kalish"}, {"date": "2018-10-10", "band": "KnowMads", "venue": "Wonder Bar", "city": "Allston", "gigname": "KnowMads"}, {"date": "2018-10-10", "band": "Such Gold", "venue": "Middle East - Upstairs", "city": "Cambridge", "gigname": "Living With Lions, Such Gold, Charmer, Heavy Sleeper"}, {"date": "2018-10-10", "band": "Charmer", "venue": "Middle East - Upstairs", "city": "Cambridge", "gigname": "Living With Lions, Such Gold, Charmer, Heavy Sleeper"}, {"date": "2018-10-10", "band": "Heavy Sleeper", "venue": "Middle East - Upstairs", "city": "Cambridge", "gigname": "Living With Lions, Such Gold, Charmer, Heavy Sleeper"}, {"date": "2018-10-10", "band": "Lauren Flaherty", "venue": "Club Passim", "city": "Cambridge", "gigname": "Lauren Balthrop"}]}